pak_eng_tagger/__init__.py
pak_eng_tagger/tagger.py
pakengtagger-0.2.1.dist-info/METADATA
pakengtagger-0.2.1.dist-info/WHEEL
pakengtagger-0.2.1.dist-info/top_level.txt
pakengtagger-0.2.1.dist-info/RECORD
