Metadata-Version: 2.2
Name: PakEngTagger
Version: 0.2.1
Summary: A POS tagger for Pakistani English developed by Muhammad Owais
Classifier: Programming Language :: Python :: 3
Classifier: License :: OSI Approved :: MIT License
Classifier: Operating System :: OS Independent
Requires-Python: >=3.12
Dynamic: classifier
Dynamic: description
Dynamic: description-content-type
Dynamic: requires-python
Dynamic: summary
